django_geopostcodes/__init__.py
django_geopostcodes/admin.py
django_geopostcodes/apps.py
django_geopostcodes/cli.py
django_geopostcodes/helpers.py
django_geopostcodes/managers.py
django_geopostcodes/models.py
django_geopostcodes/management/__init__.py
django_geopostcodes/management/commands/__init__.py
django_geopostcodes/management/commands/import_localities.py
django_geopostcodes/migrations/0001_initial.py
django_geopostcodes/migrations/0002_auto_20151021_2127.py
django_geopostcodes/migrations/__init__.py
django_geopostcodes-0.3.1.dist-info/AUTHORS.rst
django_geopostcodes-0.3.1.dist-info/LICENSE
django_geopostcodes-0.3.1.dist-info/METADATA
django_geopostcodes-0.3.1.dist-info/WHEEL
django_geopostcodes-0.3.1.dist-info/top_level.txt
django_geopostcodes-0.3.1.dist-info/RECORD
