Metadata-Version: 2.1
Name: django-geopostcodes
Version: 0.3.1
Summary: Django modelling for geopostcodes.com
Home-page: https://github.com/alexhayes/django-geopostcodes
Author: Alex Hayes
Author-email: alex@alution.com
License: MIT license
Keywords: django-geopostcodes
Classifier: Development Status :: 2 - Pre-Alpha
Classifier: Intended Audience :: Developers
Classifier: License :: OSI Approved :: MIT License
Classifier: Natural Language :: English
Classifier: Programming Language :: Python :: 3
Classifier: Programming Language :: Python :: 3.8
Classifier: Programming Language :: Python :: 3.9
Classifier: Programming Language :: Python :: 3.10
Classifier: Framework :: Django :: 2.2
Classifier: Framework :: Django :: 3.2
Classifier: Framework :: Django :: 4.0
Requires-Python: >=3.6
License-File: LICENSE
License-File: AUTHORS.rst
Requires-Dist: Django (>=2.2)
Requires-Dist: django-countries (>=7.3.2)
